maap_user_workspace_management_jupyter_extension/__init__.py
maap_user_workspace_management_jupyter_extension/_version.py
maap_user_workspace_management_jupyter_extension-0.1.5.data/data/share/jupyter/labextensions/maap-user-workspace-management-jupyter-extension/build_log.json
maap_user_workspace_management_jupyter_extension-0.1.5.data/data/share/jupyter/labextensions/maap-user-workspace-management-jupyter-extension/package.json
maap_user_workspace_management_jupyter_extension-0.1.5.data/data/share/jupyter/labextensions/maap-user-workspace-management-jupyter-extension/static/lib_index_js.79a760ba4b3703b8e5b4.js
maap_user_workspace_management_jupyter_extension-0.1.5.data/data/share/jupyter/labextensions/maap-user-workspace-management-jupyter-extension/static/lib_index_js.79a760ba4b3703b8e5b4.js.map
maap_user_workspace_management_jupyter_extension-0.1.5.data/data/share/jupyter/labextensions/maap-user-workspace-management-jupyter-extension/static/remoteEntry.3aadbc6ee1ea6dbbde20.js
maap_user_workspace_management_jupyter_extension-0.1.5.data/data/share/jupyter/labextensions/maap-user-workspace-management-jupyter-extension/static/remoteEntry.3aadbc6ee1ea6dbbde20.js.map
maap_user_workspace_management_jupyter_extension-0.1.5.data/data/share/jupyter/labextensions/maap-user-workspace-management-jupyter-extension/static/style.js
maap_user_workspace_management_jupyter_extension-0.1.5.data/data/share/jupyter/labextensions/maap-user-workspace-management-jupyter-extension/static/style_index_js.5d15ed7c70206cdd8542.js
maap_user_workspace_management_jupyter_extension-0.1.5.data/data/share/jupyter/labextensions/maap-user-workspace-management-jupyter-extension/static/style_index_js.5d15ed7c70206cdd8542.js.map
maap_user_workspace_management_jupyter_extension-0.1.5.data/data/share/jupyter/labextensions/maap-user-workspace-management-jupyter-extension/install.json
maap_user_workspace_management_jupyter_extension-0.1.5.dist-info/METADATA
maap_user_workspace_management_jupyter_extension-0.1.5.dist-info/WHEEL
maap_user_workspace_management_jupyter_extension-0.1.5.dist-info/licenses/LICENSE
maap_user_workspace_management_jupyter_extension-0.1.5.dist-info/RECORD
